<?xml version="1.0" encoding="utf-8"?>
<employees>
    <employee id="be129">
        <firstname>Jitendra</firstname>
        <lastname>Kumar</lastname>
        <title>Engineer</title>
        <division>Materials</division>
        <building>327</building>
        <room>19</room>
    </employee>
    <employee id="be130">
        <firstname>Amit</firstname>
        <lastname>Kumar</lastname>
        <title>Accountant</title>
        <division>Accts Payable</division>
        <building>326</building>
        <room>14</room>
    </employee>
    <employee id="be131">
        <firstname>Akash</firstname>
        <lastname>Kumar</lastname>
        <title>Engineering Manager</title>
        <division>Materials</division>
        <building>327</building>
        <room>21</room>
    </employee>
    <employee id="be132">
        <firstname>Aishwarya</firstname>
        <lastname>Kulshrestha</lastname>
        <title>Engineer</title>
        <division>Materials</division>
        <building>327</building>
        <room>22</room>
    </employee>
    <employee id="be133">
        <firstname>Sachin</firstname>
        <lastname>Kumar</lastname>
        <title>Engineer</title>
        <division>Materials</division>
        <building>327</building>
        <room>24</room>
    </employee>
    <employee id="be134">
        <firstname>Vikash</firstname>
        <lastname>kumar</lastname>
        <title>COO</title>
        <division>Management</division>
        <building>216</building>
        <room>26</room>
    </employee>
    <employee id="be135">
        <firstname>Suvam</firstname>
        <lastname>Basak</lastname>
        <title>Accountant</title>
        <division>Accts Payable</division>
        <building>326</building>
        <room>30</room>
    </employee>
    <employee id="be136">
        <firstname>Abhinav</firstname>
        <lastname>kumar</lastname>
        <title>COO</title>
        <division>Management</division>
        <building>216</building>
        <room>32</room>
    </employee>
     <employee id="be137">
        <firstname>DhanPal</firstname>
        <lastname>Singh</lastname>
        <title>Engineering Manager</title>
        <division>Materials</division>
        <building>327</building>
        <room>21</room>
    </employee>
     <employee id="ra001">
        <firstname>Ujjwal</firstname>
        <lastname>K.C</lastname>
        <title>Junior Engineer</title>
        <division>Materials</division>
        <building>19</building>
        <room>12</room>
    </employee>
     <employee id="ra002">
        <firstname>Bibek</firstname>
        <lastname>Kumar</lastname>
        <title>Lead Engineer</title>
        <division>Accts Payable</division>
        <building>45</building>
        <room>24</room>
    </employee>
     <employee id="ra003">
        <firstname>Raj</firstname>
        <lastname>Nagarkoti</lastname>
        <title>Designer</title>
        <division>Materials</division>
        <building>67</building>
        <room>89</room>
    </employee>
      <employee id="ra004">
        <firstname>Anoop</firstname>
        <lastname>Guragui</lastname>
        <title>Engineer</title>
        <division>Materials</division>
        <building>69</building>
        <room>11</room>
    </employee>
      <employee id="ra005">
        <firstname>Aayush</firstname>
        <lastname>Rai</lastname>
        <title>Junior Engineer</title>
        <division>Materials</division>
        <building>96</building>
        <room>34</room>
    </employee>
    <employee id="ra006">
        <firstname>Ram</firstname>
        <lastname>Tamang</lastname>
        <title>Manager</title>
        <division>Accts Payable</division>
        <building>56</building>
        <room>89</room>
    </employee>

</employees>